courseselcli/__init__.py
courseselcli/command_line.py
courseselcli/coursesel.py
courseselcli/elector.py
courseselcli/login.py
courseselcli/main.py
courseselcli/single.py
ji_coursesel-0.1.4.dist-info/METADATA
ji_coursesel-0.1.4.dist-info/WHEEL
ji_coursesel-0.1.4.dist-info/entry_points.txt
ji_coursesel-0.1.4.dist-info/top_level.txt
ji_coursesel-0.1.4.dist-info/RECORD
