Metadata-Version: 2.1
Name: ji-coursesel
Version: 0.1.4
Summary: CLI Interface for JI Coursesel
Author: linsyking
Author-email: linsy_king@sjtu.edu.cn
License: MIT License
Keywords: cli,course
Requires-Python: >=3.7
Requires-Dist: prettytable
Requires-Dist: jaccount-cli
Requires-Dist: typer
Requires-Dist: rich
